<xml xmlns="https://developers.google.com/blockly/xml"><block type="agv_init" id="y=GWFE-=LP`g[`#8^x,3" x="16" y="10"><next><block type="controls_repeat_ext" id="KIPD,pLAbGD63X2q?KlY"><value name="TIMES"><shadow type="math_number" id="uI@!Hnd]]Sdyt6]57c7]"><field name="NUM">4</field></shadow></value><statement name="DO"><block type="move_to" id="Y$ORoa$0Oc;d[fUs13rC"><value name="map_name"><block type="text" id="]TGl-|C#B$9Ak,M8,XK}"><field name="TEXT">HOKUYO_MAP</field></block></value><value name="waypoint"><block type="text" id="AWNj5tQ3Ia%6:x[K30)^"><field name="TEXT">W1</field></block></value><next><block type="sleep_type" id="vBMdVg{_kQ$d(WsYbbxM"><value name="NAME"><block type="math_number" id="9)DPWCg:czGI%H~}cA%n"><field name="NUM">5</field></block></value><next><block type="move_to" id="Wf1Y29$lpXFy1NYHp91I"><value name="map_name"><block type="text" id="vspxS13D(g4AZnJo3)uQ"><field name="TEXT">HOKUYO_MAP</field></block></value><value name="waypoint"><block type="text" id="RV_=%7)_**Vvh`^lz`jp"><field name="TEXT">W2</field></block></value><next><block type="sleep_type" id="ERy{ea+;/vKM%G;)9[k0"><value name="NAME"><block type="math_number" id="qWj%oA:7g%n4$/1,d+g+"><field name="NUM">5</field></block></value><next><block type="move_to" id="0vi6.s:.7s;aQC/tuFDu"><value name="map_name"><block type="text" id="x)$HW]zHJj^/!/W8AA(v"><field name="TEXT">HOKUYO_MAP</field></block></value><value name="waypoint"><block type="text" id="!%v!A`+NSz(GOU{/z5vC"><field name="TEXT">W3</field></block></value><next><block type="sleep_type" id="n)=:zOpyX{hGHiN~lMq^"><value name="NAME"><block type="math_number" id="{#2_QeEx2DxVZoumQC7F"><field name="NUM">5</field></block></value><next><block type="move_to" id="-$Ro:*(9(r?iU,W9//VS"><value name="map_name"><block type="text" id="}rkKrtW$a1;^QvCY:@kJ"><field name="TEXT">HOKUYO_MAP</field></block></value><value name="waypoint"><block type="text" id="Ph7c?r};lqA7Z3p~I5[V"><field name="TEXT">W4</field></block></value><next><block type="sleep_type" id="foikl_;D}Io6M|.,{3]o"><value name="NAME"><block type="math_number" id="6TtJ}.tP~-uy,yt^IRv6"><field name="NUM">5</field></block></value><next><block type="move_to" id="%%:|6rPw`vVIQn$l?B{Y"><value name="map_name"><block type="text" id=".Ss)AgW2S_/0_}%5`U3+"><field name="TEXT">HOKUYO_MAP</field></block></value><value name="waypoint"><block type="text" id="|1zdqH-63zXfrhJp}271"><field name="TEXT">W5</field></block></value><next><block type="sleep_type" id="O%GHo{Vb.gf/5eQ-fKWw"><value name="NAME"><block type="math_number" id=",%=[~CUEn(*TWLoN^_:?"><field name="NUM">5</field></block></value><next><block type="move_to" id="ZLqX3?sNt788~?ubj-]5"><value name="map_name"><block type="text" id="br[.VwBfeXH`4Q.h)6VV"><field name="TEXT">HOKUYO_MAP</field></block></value><value name="waypoint"><block type="text" id=",JPU!Bh58_P#}$XY0HY+"><field name="TEXT">W6</field></block></value><next><block type="sleep_type" id="NP(Y(%NGdx+=D|vsu`w8"><value name="NAME"><block type="math_number" id="9q/O-[P|iFIFK4emfGLa"><field name="NUM">5</field></block></value><next><block type="move_to" id="{kKwPp1EKAGE_g(u=v{c"><value name="map_name"><block type="text" id="nHS42*y7rw5a_oKQ@h@|"><field name="TEXT">HOKUYO_MAP</field></block></value><value name="waypoint"><block type="text" id="Q]Q!k7/zYC6oNyg.;N:l"><field name="TEXT">W7</field></block></value><next><block type="sleep_type" id=",`t/L7vO}joT`tne1;B+"><value name="NAME"><block type="math_number" id="nz[OsbDtf0xzhO(y~AkU"><field name="NUM">5</field></block></value></block></next></block></next></block></next></block></next></block></next></block></next></block></next></block></next></block></next></block></next></block></next></block></next></block></next></block></statement></block></next></block></xml>